MANIFEST.in
README.rst
setup.py
django_generic_m2m.egg-info/PKG-INFO
django_generic_m2m.egg-info/SOURCES.txt
django_generic_m2m.egg-info/dependency_links.txt
django_generic_m2m.egg-info/top_level.txt
genericm2m/__init__.py
genericm2m/models.py
genericm2m/utils.py
genericm2m/genericm2m_tests/__init__.py
genericm2m/genericm2m_tests/models.py
genericm2m/genericm2m_tests/tests.py
genericm2m/migrations/0001_initial.py
genericm2m/migrations/__init__.py