Metadata-Version: 1.1
Name: django-generic-m2m
Version: 0.3.1
Summary: relate anything to anything
Home-page: https://github.com/coleifer/django-generic-m2m
Author: Charles Leifer
Author-email: coleifer@gmail.com
License: UNKNOWN
Platform: UNKNOWN
Classifier: Development Status :: 4 - Beta
Classifier: Environment :: Web Environment
Classifier: Intended Audience :: Developers
Classifier: License :: OSI Approved :: MIT License
Classifier: Operating System :: OS Independent
Classifier: Programming Language :: Python
Classifier: Framework :: Django
